<annotation>
  <folder>MNIST</folder>
  <filename>000556.jpg</filename>
  <source>
    <database>MNIST database</database>
  </source>
  <size>
    <width>416</width>
    <height>416</height>
    <depth>3</depth>
  </size>
  <segmented>0</segmented>
  <object>
    <name>Coat</name>
    <pose>Unspecified</pose>
    <truncated>0</truncated>
    <difficult>0</difficult>
    <bndbox>
      <xmin>77</xmin>
      <ymin>172</ymin>
      <xmax>119</xmax>
      <ymax>214</ymax>
    </bndbox>
  </object>
  <object>
    <name>9</name>
    <pose>Unspecified</pose>
    <truncated>0</truncated>
    <difficult>0</difficult>
    <bndbox>
      <xmin>277</xmin>
      <ymin>116</ymin>
      <xmax>319</xmax>
      <ymax>158</ymax>
    </bndbox>
  </object>
  <object>
    <name>Sandal</name>
    <pose>Unspecified</pose>
    <truncated>0</truncated>
    <difficult>0</difficult>
    <bndbox>
      <xmin>198</xmin>
      <ymin>370</ymin>
      <xmax>240</xmax>
      <ymax>412</ymax>
    </bndbox>
  </object>
  <object>
    <name>5</name>
    <pose>Unspecified</pose>
    <truncated>0</truncated>
    <difficult>0</difficult>
    <bndbox>
      <xmin>148</xmin>
      <ymin>245</ymin>
      <xmax>260</xmax>
      <ymax>357</ymax>
    </bndbox>
  </object>
  <object>
    <name>6</name>
    <pose>Unspecified</pose>
    <truncated>0</truncated>
    <difficult>0</difficult>
    <bndbox>
      <xmin>20</xmin>
      <ymin>26</ymin>
      <xmax>104</xmax>
      <ymax>110</ymax>
    </bndbox>
  </object>
  <object>
    <name>Shirt</name>
    <pose>Unspecified</pose>
    <truncated>0</truncated>
    <difficult>0</difficult>
    <bndbox>
      <xmin>322</xmin>
      <ymin>241</ymin>
      <xmax>406</xmax>
      <ymax>325</ymax>
    </bndbox>
  </object>
</annotation>
