<annotation>
  <folder>MNIST</folder>
  <filename>000963.jpg</filename>
  <source>
    <database>MNIST database</database>
  </source>
  <size>
    <width>416</width>
    <height>416</height>
    <depth>3</depth>
  </size>
  <segmented>0</segmented>
  <object>
    <name>5</name>
    <pose>Unspecified</pose>
    <truncated>0</truncated>
    <difficult>0</difficult>
    <bndbox>
      <xmin>326</xmin>
      <ymin>92</ymin>
      <xmax>354</xmax>
      <ymax>120</ymax>
    </bndbox>
  </object>
  <object>
    <name>9</name>
    <pose>Unspecified</pose>
    <truncated>0</truncated>
    <difficult>0</difficult>
    <bndbox>
      <xmin>152</xmin>
      <ymin>236</ymin>
      <xmax>208</xmax>
      <ymax>292</ymax>
    </bndbox>
  </object>
  <object>
    <name>0</name>
    <pose>Unspecified</pose>
    <truncated>0</truncated>
    <difficult>0</difficult>
    <bndbox>
      <xmin>146</xmin>
      <ymin>46</ymin>
      <xmax>230</xmax>
      <ymax>130</ymax>
    </bndbox>
  </object>
</annotation>
