<annotation>
  <folder>MNIST</folder>
  <filename>000926.jpg</filename>
  <source>
    <database>MNIST database</database>
  </source>
  <size>
    <width>416</width>
    <height>416</height>
    <depth>3</depth>
  </size>
  <segmented>0</segmented>
  <object>
    <name>7</name>
    <pose>Unspecified</pose>
    <truncated>0</truncated>
    <difficult>0</difficult>
    <bndbox>
      <xmin>198</xmin>
      <ymin>65</ymin>
      <xmax>220</xmax>
      <ymax>87</ymax>
    </bndbox>
  </object>
  <object>
    <name>7</name>
    <pose>Unspecified</pose>
    <truncated>0</truncated>
    <difficult>0</difficult>
    <bndbox>
      <xmin>137</xmin>
      <ymin>85</ymin>
      <xmax>179</xmax>
      <ymax>127</ymax>
    </bndbox>
  </object>
  <object>
    <name>4</name>
    <pose>Unspecified</pose>
    <truncated>0</truncated>
    <difficult>0</difficult>
    <bndbox>
      <xmin>116</xmin>
      <ymin>158</ymin>
      <xmax>172</xmax>
      <ymax>214</ymax>
    </bndbox>
  </object>
  <object>
    <name>3</name>
    <pose>Unspecified</pose>
    <truncated>0</truncated>
    <difficult>0</difficult>
    <bndbox>
      <xmin>276</xmin>
      <ymin>237</ymin>
      <xmax>332</xmax>
      <ymax>293</ymax>
    </bndbox>
  </object>
  <object>
    <name>6</name>
    <pose>Unspecified</pose>
    <truncated>0</truncated>
    <difficult>0</difficult>
    <bndbox>
      <xmin>236</xmin>
      <ymin>92</ymin>
      <xmax>348</xmax>
      <ymax>204</ymax>
    </bndbox>
  </object>
</annotation>
